litmodels/__about__.py
litmodels/__init__.py
litmodels/demos/__init__.py
litmodels/integrations/__init__.py
litmodels/integrations/checkpoints.py
litmodels/integrations/duplicate.py
litmodels/integrations/imports.py
litmodels/integrations/mixins.py
litmodels/io/__init__.py
litmodels/io/cloud.py
litmodels/io/gateway.py
litmodels/io/utils.py
litmodels-0.1.8.dist-info/licenses/LICENSE
litmodels-0.1.8.dist-info/METADATA
litmodels-0.1.8.dist-info/WHEEL
litmodels-0.1.8.dist-info/top_level.txt
litmodels-0.1.8.dist-info/RECORD
